mcpager/__init__.py
mcpager/adapters/__init__.py
mcpager/adapters/backends.py
mcpager/client/__init__.py
mcpager/client/client.py
mcpager/client/session.py
mcpager/client/transport.py
mcpager-0.1.1.dist-info/licenses/LICENSE
mcpager-0.1.1.dist-info/METADATA
mcpager-0.1.1.dist-info/WHEEL
mcpager-0.1.1.dist-info/top_level.txt
mcpager-0.1.1.dist-info/RECORD
