Metadata-Version: 2.4
Name: mcpager
Version: 0.1.1
Summary: Pythonic MCP client
Requires-Python: >=3.10
License-File: LICENSE
Requires-Dist: fastmcp>=2.12.4
Requires-Dist: langchain>=0.3.27
Requires-Dist: langchain-openai>=0.3.35
Requires-Dist: langgraph>=0.6.10
Requires-Dist: python-dotenv>=1.1.1
Dynamic: license-file
